silta/__init__.py
silta/stm32f407.py
silta-0.4.1.dist-info/DESCRIPTION.rst
silta-0.4.1.dist-info/METADATA
silta-0.4.1.dist-info/RECORD
silta-0.4.1.dist-info/WHEEL
silta-0.4.1.dist-info/metadata.json
silta-0.4.1.dist-info/top_level.txt
