Metadata-Version: 2.0
Name: silta
Version: 0.4.1
Summary: A Python to STM32F4 Bridge Project
Home-page: https://github.com/alvarop/silta
Author: Alvaro Prieto
Author-email: silta@alvaroprieto.com
License: BSD License
Keywords: hardware firmware i2c spi gpio
Platform: UNKNOWN
Classifier: Development Status :: 3 - Alpha
Classifier: Intended Audience :: Developers
Classifier: Intended Audience :: Science/Research
Classifier: Intended Audience :: Education
Classifier: Topic :: Scientific/Engineering
Classifier: License :: OSI Approved :: BSD License
Classifier: Programming Language :: Python :: 3.6
Requires-Dist: pyserial
